LICENSE
README.md
setup.cfg
setup.py
sqlalchemy_filters/__init__.py
sqlalchemy_filters/exceptions.py
sqlalchemy_filters/fields.py
sqlalchemy_filters/filters.py
sqlalchemy_filters/mixins.py
sqlalchemy_filters/operators.py
sqlalchemy_filters/paginator.py
sqlalchemy_filters/utils.py
sqlalchemy_filters_plus.egg-info/PKG-INFO
sqlalchemy_filters_plus.egg-info/SOURCES.txt
sqlalchemy_filters_plus.egg-info/dependency_links.txt
sqlalchemy_filters_plus.egg-info/not-zip-safe
sqlalchemy_filters_plus.egg-info/top_level.txt