Metadata-Version: 2.1
Name: sqlalchemy-filters-plus
Version: 1.1.4
Summary: SQLAlchemy filters made easy
Home-page: https://github.com/elmkarami/sqlalchemy-filters-plus
Author: El Mehdi Karami
Author-email: me@elmkarami.com
License: BSD
Keywords: sqlalchemy,filter,flask,python,sql,query
Classifier: Intended Audience :: Developers
Classifier: License :: OSI Approved :: BSD License
Classifier: Programming Language :: Python :: 3.6
Classifier: Programming Language :: Python :: 3.7
Classifier: Programming Language :: Python :: 3.8
Classifier: Programming Language :: Python :: 3.9
Requires-Python: >=3.6
License-File: LICENSE
